kinova_gen3/__init__.py
kinova_gen3/dynamics/coriolis.py
kinova_gen3/dynamics/gravity.py
kinova_gen3/dynamics/mass_matrix.py
kinova_gen3/kinematics/forward_kinematics.py
kinova_gen3/kinematics/inverse_kinematics.py
kinova_gen3/kinematics/jacobian.py
kinova_gen3/performance_criteria/joint_limits.py
kinova_gen3/performance_criteria/manipulability.py
pyKinovaGen3-0.2.0.dist-info/LICENSE
pyKinovaGen3-0.2.0.dist-info/METADATA
pyKinovaGen3-0.2.0.dist-info/WHEEL
pyKinovaGen3-0.2.0.dist-info/top_level.txt
pyKinovaGen3-0.2.0.dist-info/RECORD
