Metadata-Version: 2.1
Name: pyKinovaGen3
Version: 0.2.0
Summary: Python package for the kinematics and dynamics of Kinova Gen3
Author-email: Ozan Tokatli <ozan.tokatli@gmail.com>
Project-URL: Homepage, https://github.com/pypa/sampleproject
Project-URL: Documentation, https://pykinovagen3.readthedocs.io
Project-URL: Bug Tracker, https://github.com/pypa/sampleproject/issues
Classifier: Programming Language :: Python :: 3
Classifier: License :: OSI Approved :: MIT License
Classifier: Operating System :: OS Independent
Classifier: Development Status :: 3 - Alpha
Classifier: Intended Audience :: Science/Research
Requires-Python: >=3.6
License-File: LICENSE
Requires-Dist: numpy
